jupyterspot/__init__.py
jupyterspot/_version.py
jupyterspot/labextension/build_log.json
jupyterspot/labextension/package.json
jupyterspot/labextension/schemas/jupyterspot/package.json.orig
jupyterspot/labextension/schemas/jupyterspot/plugin.json
jupyterspot/labextension/static/lib_index_js.33225c93b92a3f9894ce.js
jupyterspot/labextension/static/lib_index_js.33225c93b92a3f9894ce.js.map
jupyterspot/labextension/static/remoteEntry.4847552516ae2bf496e3.js
jupyterspot/labextension/static/remoteEntry.4847552516ae2bf496e3.js.map
jupyterspot/labextension/static/style.js
jupyterspot/labextension/static/style_index_js.fe3be13c7a94e6eaac4b.js
jupyterspot/labextension/static/style_index_js.fe3be13c7a94e6eaac4b.js.map
jupyterspot/labextension/static/vendors-node_modules_css-loader_dist_runtime_api_js-node_modules_css-loader_dist_runtime_cssW-72eba1.1523da1952301cd9bcc7.js
jupyterspot/labextension/static/vendors-node_modules_css-loader_dist_runtime_api_js-node_modules_css-loader_dist_runtime_cssW-72eba1.1523da1952301cd9bcc7.js.map
jupyterspot-0.4.0.data/data/share/jupyter/labextensions/jupyterspot/build_log.json
jupyterspot-0.4.0.data/data/share/jupyter/labextensions/jupyterspot/package.json
jupyterspot-0.4.0.data/data/share/jupyter/labextensions/jupyterspot/schemas/jupyterspot/package.json.orig
jupyterspot-0.4.0.data/data/share/jupyter/labextensions/jupyterspot/schemas/jupyterspot/plugin.json
jupyterspot-0.4.0.data/data/share/jupyter/labextensions/jupyterspot/static/lib_index_js.33225c93b92a3f9894ce.js
jupyterspot-0.4.0.data/data/share/jupyter/labextensions/jupyterspot/static/lib_index_js.33225c93b92a3f9894ce.js.map
jupyterspot-0.4.0.data/data/share/jupyter/labextensions/jupyterspot/static/remoteEntry.4847552516ae2bf496e3.js
jupyterspot-0.4.0.data/data/share/jupyter/labextensions/jupyterspot/static/remoteEntry.4847552516ae2bf496e3.js.map
jupyterspot-0.4.0.data/data/share/jupyter/labextensions/jupyterspot/static/style.js
jupyterspot-0.4.0.dist-info/METADATA
jupyterspot-0.4.0.dist-info/WHEEL
jupyterspot-0.4.0.dist-info/licenses/LICENSE
jupyterspot-0.4.0.dist-info/RECORD
